project/pd2/design/code/igen.sv
/*
 * Module: igen
 *
 * Description: Immediate value generator
 *
 * Inputs:
 * 1) opcode opcode_i
 * 2) input instruction insn_i
 * Outputs:
 * 2) 32-bit immediate value imm_o
 */

module igen #(
    parameter int DWIDTH=32
    )(
    input logic [6:0] opcode_i,
    input logic [DWIDTH-1:0] insn_i,
    output logic [31:0] imm_o
);
    
    /*
     * Process definitions to be filled by
     * student below...
     * Operating data needs to be 32-bit in order for ALU to work
     * Registers already have 32-bit data 
     */

    // Temporary Variables
    logic [11:0] store_holder;
    logic [12:0] branch_holder;
    logic [20:0] jump_holder;

    always_comb begin

        case (opcode_i)
            `Opcode_IType,
            `Opcode_IType_Jump_And_LinkReg,
            `Opcode_IType_Load: begin
                /* The 31st bit is 1 representing negative value -> assign one 20 times on the left side
                 * The 31st bit is 0 representing positive value -> assign zero 20 times on the left side
                 */
                if (insn_i[31]==1'b1) begin
                    imm_o = { 20'hFFFFF, insn_i[31:20] };
                end
                else begin
                    imm_o = { 20'h00000, insn_i[31:20] };
                end        
            end


            
            `Opcode_UType_Add_Upper_Imm,
            `Opcode_UType_Load_Upper_Imm: begin
                /* Grab 20 bits from the instruction 
                 * Add zeros 12 times on the right side because right side will be stored at different place
                 * Not adding zeros on right can create a different number we need to keep the same number (total 32 bit)
                 */
                imm_o = { insn_i[31:12], 12'h000 };       
            end

            `Opcode_SType: begin
                /* Grab the immediate value's upper and lower parts and combine them (we store 32 bits)
                 * MSB is in [31:25] and LSB in [11:7] join them using concatenation oepration { } into 12-bit number
                 * Check the 31st bit 1 or 0 and accordingly assign zeros or ones (turn into total 32 bits)
                 */
                 store_holder = {insn_i[31:25],insn_i[11:7]};
                 
                 if (insn_i[31]==1'b1) begin
                    imm_o = { 20'hFFFFF, store_holder };
                end
                else begin
                    imm_o = { 20'h00000, store_holder };
                end
            end  

            `Opcode_BType: begin
                /* Grab the immediate values and combine them in order  into 12-bit number
                 * Make the final value in 32 bits (add zeros or ones based on negative or positive numebr)
                 * The instruction must land on positive value so 1'b0
                 * manually add the 1'b0 at the end to turn our 12 bits of data into a 13-bit signed offset.
                 */     
                branch_holder = { insn_i[31], insn_i[7], insn_i[30:25], insn_i[11:8], 1'b0};
                if (insn_i[31] == 1'b1) begin
                    imm_o = { 19'h7FFFF, branch_holder }; 
                end 
                else begin
                     imm_o = { 19'h00000, branch_holder };
                end 
            end

            `Opcode_JType_Jump_And_Link: begin
                jump_holder = { insn_i[31], insn_i[19:12], insn_i[20], insn_i[30:21], 1'b0};
                if (insn_i[31] == 1'b1) begin
                    imm_o = { 11'h7FF, jump_holder }; 
                end
                else begin
                     imm_o = { 11'h000, jump_holder };
                end 
            end
            default: begin
                imm_o = 32'h00000000;
            end


        endcase
    end
endmodule : igen

project/pd2/design/code/igen_tb.sv
`timescale 1ns/1ps

module igen_tb;

    // Parameters and signals
    localparam DWIDTH = 32;
    logic [6:0]  opcode;
    logic [31:0] insn;
    logic [31:0] imm_out;
    logic [31:0] expected_imm;

    // 1. Instantiate the Unit Under Test (UUT)
    igen #( .DWIDTH(DWIDTH) ) uut (
        .opcode_i(opcode),
        .insn_i(insn),
        .imm_o(imm_out)
    );

    initial begin
        // Format for printing
        $display("Time\t Type\t\t\t\t Instruction\t Expected\t Actual\t\t Check");
        $display("--------------------------------------------------------------------------------------------------");

        // Test 1: I-Type addi
        opcode = 7'b0010011; 
        insn   = 32'hFFB10093;
        expected_imm = 32'hFFFFFFFB;
        #10;
        $display("%0t\t I-Type addi\t\t\t %H\t %H\t %H\t %s", $time, insn, expected_imm, imm_out, (imm_out === expected_imm) ? "PASS" : "FAIL !!!");
        // Test 2: I-Type Max Positive
        opcode = 7'b0010011; 
        insn = 32'h7FF00093; 
        expected_imm = 32'h000007FF;
        #10;
        $display("%0t\t I-Type Max Positive\t\t %H\t %H\t %H\t %s", $time, insn, expected_imm, imm_out, (imm_out === expected_imm) ? "PASS" : "FAIL !!!");
        
        // Test 3: I-Type Max Negative 
        opcode = 7'b0010011; 
        insn = 32'h80000093; 
        expected_imm = 32'hFFFFF800;
        #10;
        $display("%0t\t I-Type Max Negative\t\t %H\t %H\t %H\t %s", $time, insn, expected_imm, imm_out, (imm_out === expected_imm) ? "PASS" : "FAIL !!!");
        // Test 4: I-Type Zero Check
        opcode = 7'b0010011; 
        insn = 32'h00000013;
        expected_imm = 32'h00000000;
        #10;
        $display("%0t\t I-Type Zero Check\t\t %H\t %H\t %H\t %s", $time, insn, expected_imm, imm_out, (imm_out === expected_imm) ? "PASS" : "FAIL !!!");

        // Test 5: I-Type Load 
        opcode = 7'b0000011; 
        insn   = 32'h02812083;
        expected_imm = 32'h00000028;
        #10;
        $display("%0t\t I-Type Load\t\t\t %H\t %H\t %H\t %s", $time, insn, expected_imm, imm_out, (imm_out === expected_imm) ? "PASS" : "FAIL !!!");

        // Test 6: I-Type All Ones
        opcode = 7'b0010011; 
        insn = 32'hFFF00093; 
        expected_imm = 32'hFFFFFFFF;
        #10;
        $display("%0t\t I-Type All Ones\t\t %H\t %H\t %H\t %s", $time, insn, expected_imm, imm_out, (imm_out === expected_imm) ? "PASS" : "FAIL !!!");

        // Test 7: I-Type JALR with positive offset
        opcode = 7'b1100111; 
        insn   = 32'h00A100E7;
        expected_imm = 32'h0000000A;
        #10;
        $display("%0t\t I-Type JALR Positive Offset\t %H\t %H\t %H\t %s", $time, insn, expected_imm, imm_out, (imm_out === expected_imm) ? "PASS" : "FAIL !!!");
        
        // Test 8: I-Type JALR with negative offset
        opcode = 7'b1100111; 
        insn   = 32'hFFC100E7;
        expected_imm = 32'hFFFFFFFC;
        #10;
        $display("%0t\t I-Type JALR Negative Offset\t %H\t %H\t %H\t %s", $time, insn, expected_imm, imm_out, (imm_out === expected_imm) ? "PASS" : "FAIL !!!");
        
        // Test 9: S-Type Max Negative
        opcode = 7'b0100011; 
        insn = 32'h80000023;
        expected_imm = 32'hFFFFF800;
        #10;
        $display("%0t\t S-Type Max Negative\t\t %H\t %H\t %H\t %s", $time, insn, expected_imm, imm_out, (imm_out === expected_imm) ? "PASS" : "FAIL !!!");
        // Test 10: S-Type
        opcode = 7'b0100011;
        insn   = 32'h00512423;
        expected_imm = 32'h00000008; 
        #10;
        $display("%0t\t S-Type\t\t\t\t %H\t %H\t %H\t %s", $time, insn, expected_imm, imm_out, (imm_out === expected_imm) ? "PASS" : "FAIL !!!");

        // Test 11: S-Type Max Positive
        opcode = 7'b0100011; 
        insn = 32'h7E000FA3;
        expected_imm = 32'h000007FF;
        #10;
        $display("%0t\t S-Type Max Positive\t\t %H\t %H\t %H\t %s", $time, insn, expected_imm, imm_out, (imm_out === expected_imm) ? "PASS" : "FAIL !!!");
        // Test 12: S-Type Alternating Bits 
        opcode = 7'b0100011;
        insn = 32'hAAA00523;
        expected_imm = 32'hFFFFFAAA;
        #10;
        $display("%0t\t S-Type Alternating Bits\t %H\t %H\t %H\t %s", $time, insn, expected_imm, imm_out, (imm_out === expected_imm) ? "PASS" : "FAIL !!!");

        // Test 13: B-Type 
        opcode = 7'b1100011;
        insn   = 32'hFE208EE3; 
        expected_imm = 32'hFFFFFFFC;
        #10;
        $display("%0t\t B-Type\t\t\t\t %H\t %H\t %H\t %s", $time, insn, expected_imm, imm_out, (imm_out === expected_imm) ? "PASS" : "FAIL !!!");

        // Test 14: B-Type Zero Offset
        opcode = 7'b1100011; 
        insn = 32'h00000063; 
        expected_imm = 32'h00000000;
        #10;
        $display("%0t\t B-Type Zero Offset\t\t %H\t %H\t %H\t %s", $time, insn, expected_imm, imm_out, (imm_out === expected_imm) ? "PASS" : "FAIL !!!");
        
        // Test 15: B-Type Min Negative(-2)
        opcode = 7'b1100011; 
        insn = 32'hFE000FE3;
        expected_imm = 32'hFFFFFFFE;
        #10;
        $display("%0t\t B-Type Min Negative\t\t %H\t %H\t %H\t %s", $time, insn, expected_imm, imm_out, (imm_out === expected_imm) ? "PASS" : "FAIL !!!");

        // Test 16: B-Type Max Negative 
        opcode = 7'b1100011; 
        insn = 32'h80000063; 
        expected_imm = 32'hFFFFF000;
        #10;
        $display("%0t\t B-Type Max Negative\t\t %H\t %H\t %H\t %s", $time, insn, expected_imm, imm_out, (imm_out === expected_imm) ? "PASS" : "FAIL !!!");

        // Test 17: B-Type Bit 11 Verification (Instruction bit 7 > Immediate bit 11)
        opcode = 7'b1100011;
        insn = 32'h000000E3;
        expected_imm = 32'h00000800;
        #10;
        $display("%0t\t B-Type Bit 11\t\t\t %H\t %H\t %H\t %s", $time, insn, expected_imm, imm_out, (imm_out === expected_imm) ? "PASS" : "FAIL !!!");

        // Test 18: B-Type Max Positive 
        opcode = 7'b1100011;
        insn = 32'h7E000F63;
        expected_imm = 32'h000007FE;
        #10;
        $display("%0t\t B-Type Max Positive\t\t %H\t %H\t %H\t %s", $time, insn, expected_imm, imm_out, (imm_out === expected_imm) ? "PASS" : "FAIL !!!");
        //Test 19: J-Type
        opcode = 7'b1101111;
        insn   = 32'h001000ef; 
        expected_imm = 32'h00000800;
        #10;
        $display("%0t\t J-Type\t\t\t\t %H\t %H\t %H\t %s", $time, insn, expected_imm, imm_out, (imm_out === expected_imm) ? "PASS" : "FAIL !!!");

        // Test 20: J-Type Max Positive Jump
        opcode = 7'b1101111;
        insn   = 32'h7FFFF0EF;
        expected_imm = 32'h000FFFFE;
        #10;
        $display("%0t\t J-Type Max Positive Jump\t %H\t %H\t %H\t %s", $time, insn, expected_imm, imm_out, (imm_out === expected_imm) ? "PASS" : "FAIL !!!");

        // Test 21: J-Type Maximum Negative Jump
        opcode = 7'b1101111;
        insn = 32'h800000ef;
        expected_imm = 32'hFFF00000;
        #10;
        $display("%0t\t J-Type Maximum Negative Jump\t %H\t %H\t %H\t %s", $time, insn, expected_imm, imm_out, (imm_out === expected_imm) ? "PASS" : "FAIL !!!");
        //Test 22: J-Type Bit 12 confirms instruction bits 19:12 map to immediate bits 19:12
        opcode = 7'b1101111;
        insn = 32'h000010ef;
        expected_imm = 32'h00001000;
        #10;
        $display("%0t\t J-Bit12\t\t\t %H\t %H\t %H\t %s", $time, insn, expected_imm, imm_out, (imm_out === expected_imm) ? "PASS" : "FAIL !!!");
        
        // Test 23: smallest Jump (+2) check instruction bit 21 maps to immediate bit 1 (bit 0 is always 0)
        opcode = 7'b1101111;
        insn = 32'h002000ef;
        expected_imm = 32'h00000002;
        #10;
        $display("%0t\t J-Small\t\t\t %H\t %H\t %H\t %s", $time, insn, expected_imm, imm_out, (imm_out === expected_imm) ? "PASS" : "FAIL !!!");
        // Test 24: U-Type
        opcode = 7'b0110111;
        insn   = 32'h123450B7;
        expected_imm = 32'h12345000;
        #10;
        $display("%0t\t U-Type\t\t\t\t %H\t %H\t %H\t %s", $time, insn, expected_imm, imm_out, (imm_out === expected_imm) ? "PASS" : "FAIL !!!");
        
        // Test 25: U-Type Maximum 
        opcode = 7'b0110111;
        insn = 32'hFFFFF0B7;
        expected_imm = 32'hFFFFF000;
        #10;
        $display("%0t\t U-Type Maximum\t\t\t %H\t %H\t %H\t %s", $time, insn, expected_imm, imm_out, (imm_out === expected_imm) ? "PASS" : "FAIL !!!");

        // Test 26: U-Type Minimum
        opcode = 7'b0110111;
        insn = 32'h000010b7;
        expected_imm = 32'h00001000;
        #10;
        $display("%0t\t U-Min\t\t\t\t %H\t %H\t %H\t %s", $time, insn, expected_imm, imm_out, (imm_out === expected_imm) ? "PASS" : "FAIL !!!");
        //Test 27: U-Type Padding and Bit Capture Check
        opcode = 7'b0010111;
        insn = 32'hABCDE097;
        expected_imm = 32'hABCDE000;
        #10;
        $display("%0t\t U-Type Padding_Bits\t\t %H\t %H\t %H\t %s", $time, insn, expected_imm, imm_out, (imm_out === expected_imm) ? "PASS" : "FAIL !!!");
        
        //Test 28: U-Type MSB Only checks that bit 31 of the instruction maps to bit 31 of the output 
        opcode = 7'b0110111;
        insn = 32'h800000B7;
        expected_imm = 32'h80000000;
        #10;
        $display("%0t\t U-Type-MSB\t\t\t %H\t %H\t %H\t %s", $time, insn, expected_imm, imm_out, (imm_out === expected_imm) ? "PASS" : "FAIL !!!");

        // Test 29: Default Case (R-Type)
        opcode = 7'b0110011;
        insn   = 32'h00A582B3;
        expected_imm = 32'h00000000; 
        #10;
        $display("%0t\t Default/R-Type\t\t\t %H\t %H\t %H\t %s", $time, insn, expected_imm, imm_out, (imm_out === expected_imm) ? "PASS" : "FAIL !!!");

        $display("--------------------------------------------------------------------------------------------------");
        $finish;
    end

endmodule

project/pd2/design/code/igen_waves.vcd
$date
	Thu Feb  5 21:40:42 2026
$end
$version
	Icarus Verilog
$end
$timescale
	1ps
$end
$scope module igen_tb $end
$var wire 32 ! imm_out [31:0] $end
$var parameter 32 " DWIDTH $end
$var reg 32 # expected_imm [31:0] $end
$var reg 32 $ insn [31:0] $end
$var reg 7 % opcode [6:0] $end
$scope module uut $end
$var wire 32 & insn_i [31:0] $end
$var wire 7 ' opcode_i [6:0] $end
$var parameter 32 ( DWIDTH $end
$var reg 13 ) branch_holder [12:0] $end
$var reg 32 * imm_o [31:0] $end
$var reg 21 + jump_holder [20:0] $end
$var reg 12 , store_holder [11:0] $end
$upscope $end
$upscope $end
$enddefinitions $end
$comment Show the parameter values. $end
$dumpall
b100000 (
b100000 "
$end
#0
$dumpvars
bx ,
bx +
b11111111111111111111111111111011 *
bx )
b10011 '
b11111111101100010000000010010011 &
b10011 %
b11111111101100010000000010010011 $
b11111111111111111111111111111011 #
b11111111111111111111111111111011 !
$end
#10000
b11111111111 !
b11111111111 *
b11111111111 #
b1111111111100000000000010010011 $
b1111111111100000000000010010011 &
#20000
b11111111111111111111100000000000 !
b11111111111111111111100000000000 *
b11111111111111111111100000000000 #
b10000000000000000000000010010011 $
b10000000000000000000000010010011 &
#30000
b0 !
b0 *
b0 #
b10011 $
b10011 &
#40000
b101000 !
b101000 *
b101000 #
b10100000010010000010000011 $
b10100000010010000010000011 &
b11 %
b11 '
#50000
b11111111111111111111111111111111 !
b11111111111111111111111111111111 *
b11111111111111111111111111111111 #
b11111111111100000000000010010011 $
b11111111111100000000000010010011 &
b10011 %
b10011 '
#60000
b1010 !
b1010 *
b1010 #
b101000010000000011100111 $
b101000010000000011100111 &
b1100111 %
b1100111 '
#70000
b11111111111111111111111111111100 !
b11111111111111111111111111111100 *
b11111111111111111111111111111100 #
b11111111110000010000000011100111 $
b11111111110000010000000011100111 &
#80000
b11111111111111111111100000000000 !
b11111111111111111111100000000000 *
b100000000000 ,
b11111111111111111111100000000000 #
b10000000000000000000000000100011 $
b10000000000000000000000000100011 &
b100011 %
b100011 '
#90000
b1000 !
b1000 *
b1000 ,
b1000 #
b10100010010010000100011 $
b10100010010010000100011 &
#100000
b11111111111 !
b11111111111 *
b11111111111 ,
b11111111111 #
b1111110000000000000111110100011 $
b1111110000000000000111110100011 &
#110000
b11111111111111111111101010101010 !
b11111111111111111111101010101010 *
b101010101010 ,
b11111111111111111111101010101010 #
b10101010101000000000010100100011 $
b10101010101000000000010100100011 &
#120000
b11111111111111111111111111111100 !
b11111111111111111111111111111100 *
b1111111111100 )
b11111111111111111111111111111100 #
b11111110001000001000111011100011 $
b11111110001000001000111011100011 &
b1100011 %
b1100011 '
#130000
b0 !
b0 *
b0 )
b0 #
b1100011 $
b1100011 &
#140000
b11111111111111111111111111111110 !
b11111111111111111111111111111110 *
b1111111111110 )
b11111111111111111111111111111110 #
b11111110000000000000111111100011 $
b11111110000000000000111111100011 &
#150000
b11111111111111111111000000000000 !
b11111111111111111111000000000000 *
b1000000000000 )
b11111111111111111111000000000000 #
b10000000000000000000000001100011 $
b10000000000000000000000001100011 &
#160000
b100000000000 !
b100000000000 *
b100000000000 )
b100000000000 #
b11100011 $
b11100011 &
#170000
b11111111110 !
b11111111110 *
b11111111110 )
b11111111110 #
b1111110000000000000111101100011 $
b1111110000000000000111101100011 &
#180000
b100000000000 !
b100000000000 *
b100000000000 +
b100000000000 #
b100000000000011101111 $
b100000000000011101111 &
b1101111 %
b1101111 '
#190000
b11111111111111111110 !
b11111111111111111110 *
b11111111111111111110 +
b11111111111111111110 #
b1111111111111111111000011101111 $
b1111111111111111111000011101111 &
#200000
b11111111111100000000000000000000 !
b11111111111100000000000000000000 *
b100000000000000000000 +
b11111111111100000000000000000000 #
b10000000000000000000000011101111 $
b10000000000000000000000011101111 &
#210000
b1000000000000 !
b1000000000000 *
b1000000000000 +
b1000000000000 #
b1000011101111 $
b1000011101111 &
#220000
b10 !
b10 *
b10 +
b10 #
b1000000000000011101111 $
b1000000000000011101111 &
#230000
b10010001101000101000000000000 !
b10010001101000101000000000000 *
b10010001101000101000000000000 #
b10010001101000101000010110111 $
b10010001101000101000010110111 &
b110111 %
b110111 '
#240000
b11111111111111111111000000000000 !
b11111111111111111111000000000000 *
b11111111111111111111000000000000 #
b11111111111111111111000010110111 $
b11111111111111111111000010110111 &
#250000
b1000000000000 !
b1000000000000 *
b1000000000000 #
b1000010110111 $
b1000010110111 &
#260000
b10101011110011011110000000000000 !
b10101011110011011110000000000000 *
b10101011110011011110000000000000 #
b10101011110011011110000010010111 $
b10101011110011011110000010010111 &
b10111 %
b10111 '
#270000
b10000000000000000000000000000000 !
b10000000000000000000000000000000 *
b10000000000000000000000000000000 #
b10000000000000000000000010110111 $
b10000000000000000000000010110111 &
b110111 %
b110111 '
#280000
b0 !
b0 *
b0 #
b101001011000001010110011 $
b101001011000001010110011 &
b110011 %
b110011 '
